codecs_protocol/__init__.py
codecs_protocol/codec.py
codecs_protocol/helper.py
codecs_protocol-1.0.2.dist-info/METADATA
codecs_protocol-1.0.2.dist-info/WHEEL
codecs_protocol-1.0.2.dist-info/top_level.txt
codecs_protocol-1.0.2.dist-info/RECORD
