Metadata-Version: 2.2
Name: codecs_protocol
Version: 1.0.2
Summary: A Python library for decoding AVL packets (Codec8 & Codec8E).
Author: Chandan Sharma
Author-email: chandansharma7012@gmail.com
Classifier: Programming Language :: Python :: 3
Classifier: License :: OSI Approved :: MIT License
Classifier: Operating System :: OS Independent
Requires-Python: >=3.6
Dynamic: author
Dynamic: author-email
Dynamic: classifier
Dynamic: description-content-type
Dynamic: requires-python
Dynamic: summary
